spydertop/__init__.py
spydertop/cli.py
spydertop/model.py
spydertop/recordpool.py
spydertop/state.py
spydertop/config/__init__.py
spydertop/config/cache.py
spydertop/config/config.py
spydertop/config/secrets.py
spydertop/constants/__init__.py
spydertop/constants/columns.py
spydertop/constants/palettes.py
spydertop/screens/__init__.py
spydertop/screens/config.py
spydertop/screens/failure.py
spydertop/screens/feedback.py
spydertop/screens/footer.py
spydertop/screens/help.py
spydertop/screens/loading.py
spydertop/screens/main.py
spydertop/screens/meters.py
spydertop/screens/modals.py
spydertop/screens/quit.py
spydertop/screens/setup.py
spydertop/utils/__init__.py
spydertop/utils/cursorlist.py
spydertop/utils/types.py
spydertop/widgets/__init__.py
spydertop/widgets/form.py
spydertop/widgets/meter.py
spydertop/widgets/table.py
spydertop-1.4.0.dist-info/LICENSE
spydertop-1.4.0.dist-info/METADATA
spydertop-1.4.0.dist-info/WHEEL
spydertop-1.4.0.dist-info/entry_points.txt
spydertop-1.4.0.dist-info/top_level.txt
spydertop-1.4.0.dist-info/RECORD
