Metadata-Version: 2.2
Name: spydertop
Version: 1.4.0
Summary: A tool that provides htop-like functionality for any point in time.
Author-email: Griffith Thomas <dev@spyderbat.com>
Maintainer-email: Spyderbat <dev@spyderbat.com>
License: The MIT License (MIT)
Project-URL: Source, https://github.com/spyderbat/spydertop
Project-URL: Spyderbat, https://www.spyderbat.com/
Project-URL: Docker, https://hub.docker.com/r/spyderbat/spydertop
Keywords: spydertop,spyderbat,htop,top
Classifier: Environment :: Console
Classifier: Intended Audience :: Information Technology
Classifier: License :: OSI Approved :: MIT License
Classifier: Natural Language :: English
Requires-Python: >=3.8
License-File: LICENSE
Requires-Dist: asciimatics
Requires-Dist: click
Requires-Dist: pyyaml
Requires-Dist: pyperclip
Requires-Dist: dateparser
Requires-Dist: platformdirs
Requires-Dist: urllib3
Requires-Dist: orjson
